taskwatcher/__init__.py
taskwatcher/control.py
taskwatcher/database.py
taskwatcher/launch.py
taskwatcher/parse.py
taskwatcher/testprog.py
taskwatcher-1.7.dist-info/LICENSE
taskwatcher-1.7.dist-info/METADATA
taskwatcher-1.7.dist-info/WHEEL
taskwatcher-1.7.dist-info/top_level.txt
taskwatcher-1.7.dist-info/RECORD
